TRI_LBM/__init__.py
TRI_LBM/lbm.py
tri_lbm-0.0.43.dist-info/licenses/LICENSE
tri_lbm-0.0.43.dist-info/METADATA
tri_lbm-0.0.43.dist-info/WHEEL
tri_lbm-0.0.43.dist-info/top_level.txt
tri_lbm-0.0.43.dist-info/RECORD
