Metadata-Version: 2.4
Name: TRI-LBM
Version: 0.0.43
Summary: Large Behavioral Model from Toyota Research
Author-email: Phil Wang <lucidrains@gmail.com>
License-Expression: MIT
Project-URL: Homepage, https://pypi.org/project/TRI-LBM/
Project-URL: Repository, https://github.com/lucidrains/TRI-LBM
Keywords: artificial intelligence,deep learning,transformers,attention mechanism,diffusion,robotic dexterity
Classifier: Development Status :: 4 - Beta
Classifier: Intended Audience :: Developers
Classifier: Topic :: Scientific/Engineering :: Artificial Intelligence
Classifier: Programming Language :: Python :: 3.9
Requires-Python: >=3.9
License-File: LICENSE
Requires-Dist: bidirectional-cross-attention>=0.1.0
Requires-Dist: denoising-diffusion-pytorch>=2.2.4
Requires-Dist: einx>=0.3.0
Requires-Dist: einops>=0.8.0
Requires-Dist: open_clip_torch
Requires-Dist: x-transformers>=2.6.7
Requires-Dist: vit-pytorch>=1.11.2
Provides-Extra: examples
Provides-Extra: test
Requires-Dist: pytest; extra == "test"
Dynamic: license-file
